compressfiles/__init__.py
compressfiles/compressfiles.py
compressfiles-0.0.4.dist-info/License.txt
compressfiles-0.0.4.dist-info/METADATA
compressfiles-0.0.4.dist-info/WHEEL
compressfiles-0.0.4.dist-info/top_level.txt
compressfiles-0.0.4.dist-info/RECORD
