Metadata-Version: 2.1
Name: compressfiles
Version: 0.0.4
Summary: Library used to compress files using gzip but more simple
Home-page: https://github.com/Alleexx129/txt-compressor
Author: Alleexx
Author-email: alleexx129@gmail.com
Project-URL: Bug Tracker, https://github.com/Alleexx129/txt-compressor/issues
Classifier: Programming Language :: Python :: 3
Classifier: License :: OSI Approved :: MIT License
Classifier: Operating System :: OS Independent
Requires-Python: >=3.6
License-File: License.txt
